scikit_hep_repo_review/__init__.py
scikit_hep_repo_review/__main__.py
scikit_hep_repo_review/families.py
scikit_hep_repo_review/fixtures.py
scikit_hep_repo_review/ghpath.py
scikit_hep_repo_review/processor.py
scikit_hep_repo_review/py.typed
scikit_hep_repo_review/_compat/__init__.py
scikit_hep_repo_review/_compat/tomllib.py
scikit_hep_repo_review/_compat/importlib/__init__.py
scikit_hep_repo_review/_compat/importlib/resources/__init__.py
scikit_hep_repo_review/_compat/importlib/resources/abc.py
scikit_hep_repo_review/checks/__init__.py
scikit_hep_repo_review/checks/general.py
scikit_hep_repo_review/checks/github.py
scikit_hep_repo_review/checks/mypy.py
scikit_hep_repo_review/checks/precommit.py
scikit_hep_repo_review/checks/pyproject.py
scikit_hep_repo_review/checks/ruff.py
scikit_hep_repo_review-0.6.1.dist-info/METADATA
scikit_hep_repo_review-0.6.1.dist-info/WHEEL
scikit_hep_repo_review-0.6.1.dist-info/entry_points.txt
scikit_hep_repo_review-0.6.1.dist-info/licenses/LICENSE
scikit_hep_repo_review-0.6.1.dist-info/RECORD
