Metadata-Version: 2.1
Name: scikit_hep_repo_review
Version: 0.6.1
Summary: Review repos for compliance to the Scikit-HEP developer guidelines
Project-URL: homepage, https://github.com/Scikit-HEP/repo-review
Project-URL: webpage, https://scikit-hep.github.io/repo-review
Author-email: Henry Schreiner <henryfs@princeton.edu>
Maintainer-email: The Scikit-HEP admins <scikit-hep-admins@googlegroups.com>
License: BSD 3-Clause License
License-File: LICENSE
Classifier: Development Status :: 4 - Beta
Classifier: Intended Audience :: Developers
Classifier: Intended Audience :: Science/Research
Classifier: License :: OSI Approved :: BSD License
Classifier: Operating System :: OS Independent
Classifier: Programming Language :: Python
Classifier: Programming Language :: Python :: 3
Classifier: Programming Language :: Python :: 3.10
Classifier: Programming Language :: Python :: 3.11
Classifier: Programming Language :: Python :: 3.12
Classifier: Topic :: Scientific/Engineering
Requires-Python: >=3.10
Requires-Dist: markdown-it-py
Requires-Dist: pyyaml
Requires-Dist: tomli; python_version < '3.11'
Provides-Extra: cli
Requires-Dist: click>=8; extra == 'cli'
Requires-Dist: rich>=12.2; extra == 'cli'
Provides-Extra: dev
Requires-Dist: pytest>=7; extra == 'dev'
Provides-Extra: test
Requires-Dist: pytest>=7; extra == 'test'
